README.md
setup.py
dqwrap/__init__.py
dqwrap/error.py
dqwrap/logger.py
dqwrap.egg-info/PKG-INFO
dqwrap.egg-info/SOURCES.txt
dqwrap.egg-info/dependency_links.txt
dqwrap.egg-info/not-zip-safe
dqwrap.egg-info/requires.txt
dqwrap.egg-info/top_level.txt
dqwrap/dbs/__init__.py
dqwrap/dbs/basedao.py
dqwrap/dbs/basedbwrap.py
dqwrap/dbs/mssqlwrap.py
dqwrap/dbs/mysqlwrap.py
dqwrap/dbs/oraclewrap.py
dqwrap/dbs/pools.py
dqwrap/dbs/postgrewrap.py
dqwrap/dbs/redisdao.py
dqwrap/dbs/rediswrap.py
dqwrap/utils/__init__.py
dqwrap/utils/collectionutil.py
dqwrap/utils/hashutil.py
dqwrap/utils/jsonutil.py
dqwrap/utils/randutil.py
dqwrap/utils/sqlutil.py
dqwrap/utils/timeutil.py