Metadata-Version: 2.1
Name: dqwrap
Version: 0.0.2
Summary: wrap layer of 5-lay architecture
Home-page: http://assetik.com
Author: daqian
Author-email: daqian.zhang@g42.ai
License: MIT Licence
Keywords: wrap,5-layer,wrap layer
Platform: any
Requires-Python: >=3.5.0
